setup.py
dm/__init__.py
dm.iter.egg-info/PKG-INFO
dm.iter.egg-info/SOURCES.txt
dm.iter.egg-info/dependency_links.txt
dm.iter.egg-info/namespace_packages.txt
dm.iter.egg-info/top_level.txt
dm.iter.egg-info/zip-safe
dm/iter/LICENSE.txt
dm/iter/README.txt
dm/iter/VERSION.txt
dm/iter/__init__.py
dm/iter/relation.py
dm/iter/tests.py