Metadata-Version: 1.0
Name: dm.iter
Version: 1.0
Summary: Some iterator utilities
Home-page: http://pypi.python.org/pypi/dm.iter
Author: Dieter Maurer
Author-email: dieter@handshake.de
License: BSD (see "dm/iter/LICENSE.txt", for details)
Keywords: iter closure
Platform: UNKNOWN
Classifier: Development Status :: 5 - Production/Stable
Classifier: Intended Audience :: Developers
Classifier: License :: OSI Approved :: BSD License
Classifier: Operating System :: OS Independent
Classifier: Programming Language :: Python
Classifier: Topic :: Software Development
Classifier: Topic :: Utilities
